tornado_swirl/__init__.py
tornado_swirl/_parser_model.py
tornado_swirl/docparser.py
tornado_swirl/handlers.py
tornado_swirl/settings.py
tornado_swirl/swagger.py
tornado_swirl/views.py
tornado_swirl/openapi/__init__.py
tornado_swirl/openapi/types.py
tornado_swirl/static/README.md
tornado_swirl/static/absolute-path.js
tornado_swirl/static/favicon-16x16.png
tornado_swirl/static/favicon-32x32.png
tornado_swirl/static/index.html
tornado_swirl/static/index.js
tornado_swirl/static/oauth2-redirect.html
tornado_swirl/static/package.json
tornado_swirl/static/swagger-ui-bundle.js
tornado_swirl/static/swagger-ui-bundle.js.map
tornado_swirl/static/swagger-ui-standalone-preset.js
tornado_swirl/static/swagger-ui-standalone-preset.js.map
tornado_swirl/static/swagger-ui.css
tornado_swirl/static/swagger-ui.css.map
tornado_swirl/static/swagger-ui.js
tornado_swirl/static/swagger-ui.js.map
ecs_lib_tornado_swirl-0.0.1.dist-info/LICENSE
ecs_lib_tornado_swirl-0.0.1.dist-info/METADATA
ecs_lib_tornado_swirl-0.0.1.dist-info/WHEEL
ecs_lib_tornado_swirl-0.0.1.dist-info/top_level.txt
ecs_lib_tornado_swirl-0.0.1.dist-info/RECORD
